etl_bq_tools/__init__.py
etl_bq_tools/functions/__init__.py
etl_bq_tools/functions/bigquery.py
etl_bq_tools/functions/bq.py
etl_bq_tools/functions/cloud_storage.py
etl_bq_tools/functions/dataframe.py
etl_bq_tools/functions/dataset.py
etl_bq_tools/utils/__init__.py
etl_bq_tools/utils/constants.py
etl_bq_tools/utils/logger.py
etl_bq_tools/utils/memory.py
etl_bq_tools/utils/prettytable.py
etl_bq_tools/utils/time_execution.py
etl_bq_tools-0.0.23.dist-info/LICENSE
etl_bq_tools-0.0.23.dist-info/METADATA
etl_bq_tools-0.0.23.dist-info/WHEEL
etl_bq_tools-0.0.23.dist-info/top_level.txt
etl_bq_tools-0.0.23.dist-info/RECORD
